src/FastaUtils.py
src/__init__.py
src/assemblyStatistics.py
tests/__init__.py
tests/test_module.py
assemblyStatistics-1.1.3.dist-info/LICENSE
assemblyStatistics-1.1.3.dist-info/METADATA
assemblyStatistics-1.1.3.dist-info/WHEEL
assemblyStatistics-1.1.3.dist-info/entry_points.txt
assemblyStatistics-1.1.3.dist-info/top_level.txt
assemblyStatistics-1.1.3.dist-info/RECORD
