Metadata-Version: 2.1
Name: assemblyStatistics
Version: 1.1.3
Summary: A script to evaluate the assembly of a given genome.
Home-page: https://github.com/WenchaoLin/assemblyStatistics
Author: Wenchao Lin
Author-email: Wenchao Lin <linwenchao@yeah.net>
License: GNU GENERAL PUBLIC LICENSE
Project-URL: Homepage, https://github.com/WenchaoLin/assemblyStatistics
Project-URL: Bug Tracker, https://github.com/WenchaoLin/assemblyStatistics/issues
Keywords: assembly,scaffolds
Classifier: Programming Language :: Python :: 3
Classifier: License :: OSI Approved :: GNU General Public License v3 (GPLv3)
Classifier: Operating System :: OS Independent
Classifier: Programming Language :: Python
Classifier: Programming Language :: Python :: 3.6
Classifier: Programming Language :: Python :: 3.7
Classifier: Programming Language :: Python :: 3.8
Requires-Python: >=3.7
License-File: LICENSE
